easyrepr/__init__.py
easyrepr/decorator.py
easyrepr/descriptor.py
easyrepr/reflection.py
easyrepr/style.py
easyrepr-0.4.0.dist-info/LICENSE.rst
easyrepr-0.4.0.dist-info/WHEEL
easyrepr-0.4.0.dist-info/METADATA
easyrepr-0.4.0.dist-info/RECORD
